pubkeeper/brew/zmq/__init__.py
pubkeeper/brew/zmq/brew.py
pubkeeper/brew/zmq/driver/__init__.py
pubkeeper/brew/zmq/driver/listener.py
pubkeeper/brew/zmq/driver/manager.py
pubkeeper/brew/zmq/driver/queue.py
pubkeeper/brew/zmq/driver/socket_options.py
pubkeeper/brew/zmq/driver/encryption/__init__.py
pubkeeper/brew/zmq/driver/encryption/context.py
pubkeeper/brew/zmq/driver/encryption/encryption.py
pubkeeper.brew.zmq-1.0.0.dist-info/DESCRIPTION.rst
pubkeeper.brew.zmq-1.0.0.dist-info/METADATA
pubkeeper.brew.zmq-1.0.0.dist-info/RECORD
pubkeeper.brew.zmq-1.0.0.dist-info/WHEEL
pubkeeper.brew.zmq-1.0.0.dist-info/metadata.json
pubkeeper.brew.zmq-1.0.0.dist-info/top_level.txt
