Metadata-Version: 2.0
Name: pubkeeper.brew.zmq
Version: 1.0.0
Summary: Brew, Consume, ZMQ!
Home-page: http://github.com/pubkeeper/python-brew-zmq
Author: n.io
Author-email: info@n.io
License: UNKNOWN
Keywords: pubkeeper,python-brew-zmq
Platform: UNKNOWN
Classifier: License :: Other/Proprietary License
Classifier: Programming Language :: Python :: 3
Classifier: Programming Language :: Python :: 3.5
Requires-Dist: pubkeeper.client (~=1.0)
Requires-Dist: pyzmq (~=14.7)
